toelis.py
toelis-2.1.4.dist-info/COPYING
toelis-2.1.4.dist-info/METADATA
toelis-2.1.4.dist-info/WHEEL
toelis-2.1.4.dist-info/top_level.txt
toelis-2.1.4.dist-info/RECORD
